pybuilder_pytest/__init__.py
pybuilder_pytest-1.1.3.dist-info/DESCRIPTION.rst
pybuilder_pytest-1.1.3.dist-info/METADATA
pybuilder_pytest-1.1.3.dist-info/RECORD
pybuilder_pytest-1.1.3.dist-info/WHEEL
pybuilder_pytest-1.1.3.dist-info/metadata.json
pybuilder_pytest-1.1.3.dist-info/namespace_packages.txt
pybuilder_pytest-1.1.3.dist-info/top_level.txt
pybuilder_pytest-1.1.3.dist-info/zip-safe
